interface/__init__.py
interface/__version__.py
interface/exceptions.py
interface/interface.py
python_interfaces-0.1.2.dist-info/LICENSE
python_interfaces-0.1.2.dist-info/METADATA
python_interfaces-0.1.2.dist-info/WHEEL
python_interfaces-0.1.2.dist-info/top_level.txt
python_interfaces-0.1.2.dist-info/RECORD
