Metadata-Version: 2.1
Name: python-interfaces
Version: 0.1.2
Summary: Bringing interfaces to Python.
Home-page: https://github.com/tyleragreen/python-interfaces
Author: Tyler Green
Author-email: greent@tyleragreen.com
License: MIT license
Platform: UNKNOWN
